README.md
setup.py
AutoMarker.egg-info/PKG-INFO
AutoMarker.egg-info/SOURCES.txt
AutoMarker.egg-info/dependency_links.txt
AutoMarker.egg-info/requires.txt
AutoMarker.egg-info/top_level.txt
automarker/__init__.py
automarker/config.py
automarker/marker.py
automarker/utils.py