Metadata-Version: 2.1
Name: AutoMarker
Version: 0.0.1.2
Summary: Terry Auto Marker
Home-page: https://github.com/napoler/AlBert-BiLSTM-CRF-pytorch
Author: Terry Chan
Author-email: napoler2008@gmail.com
License: UNKNOWN
Platform: UNKNOWN
